MANIFEST.in
setup.py
blankslate/.env
blankslate/Procfile
blankslate/__init__.py
blankslate/cli.py
blankslate/commands.py
blankslate/download.py
blankslate/logging.py
blankslate/run.sh
blankslate.egg-info/PKG-INFO
blankslate.egg-info/SOURCES.txt
blankslate.egg-info/dependency_links.txt
blankslate.egg-info/entry_points.txt
blankslate.egg-info/requires.txt
blankslate.egg-info/top_level.txt
blankslate/scripts/argparse.sh
blankslate/scripts/commands.sh
blankslate/slates/bootstrap/slate.sh
blankslate/slates/bootstrap/config/haproxy.cfg
blankslate/slates/django-haproxy/README.md
blankslate/slates/django-haproxy/slate.json
blankslate/slates/django-haproxy/slate.sh
blankslate/slates/django-react/.babelrc
blankslate/slates/django-react/README.md
blankslate/slates/django-react/server.js
blankslate/slates/django-react/slate.json
blankslate/slates/django-react/slate.sh
blankslate/slates/django-react/webpack.config.js
blankslate/slates/django-react/assets/js/app.jsx
blankslate/slates/django-react/assets/js/index.jsx
blankslate/slates/django-react/project/urls.py
blankslate/slates/django-react/templates/home.html
blankslate/slates/example/Procfile
blankslate/slates/example/README.md
blankslate/slates/example/packages
blankslate/slates/example/slate.sh
blankslate/slates/example-ansible/README.md
blankslate/slates/example-ansible/play.yml
blankslate/slates/example-ansible/slate.sh
blankslate/slates/example/config/haproxy.cfg
blankslate/slates/example/config/package.json
blankslate/slates/example/config/requirements_py2django.txt
blankslate/slates/example/config/requirements_py3django.txt
blankslate/slates/example/config/requirements_pypydjango.txt
blankslate/slates/example/go/hello-world.go
blankslate/slates/example/nodejs/server.js
blankslate/slates/pypy/slate.json
blankslate/slates/pypy/slate.sh
blankslate/slates/virtualenv/slate.json
blankslate/slates/virtualenv/slate.sh