Metadata-Version: 1.0
Name: blankslate
Version: 0.1.10
Summary: Blank Slate - A foundation for complex projects
Home-page: http://github.com/futurice/blankslate
Author: Jussi Vaihia
Author-email: jussi.vaihia@futurice.com
License: BSD
Keywords: blankslate blank slate
Platform: UNKNOWN
